Metadata-Version: 1.0
Name: rk-distributions
Version: 0.1
Summary: Gaussian distributions
Home-page: UNKNOWN
Author: Raghavendra Kulkarni
Author-email: rdkulkarni@gmail.com
License: UNKNOWN
Platform: UNKNOWN
